pyconafrica.py
pyconafrica-1.0.2.dist-info/LICENSE
pyconafrica-1.0.2.dist-info/WHEEL
pyconafrica-1.0.2.dist-info/METADATA
pyconafrica-1.0.2.dist-info/RECORD
